rudi_node_write/__init__.py
rudi_node_write/rudi_node_writer.py
rudi_node_write/conf/meta_defaults.py
rudi_node_write/connectors/io_connector.py
rudi_node_write/connectors/io_rudi_catalog_write.py
rudi_node_write/connectors/io_rudi_jwt_factory.py
rudi_node_write/connectors/io_rudi_manager_write.py
rudi_node_write/connectors/io_rudi_manager_write_v2.py
rudi_node_write/connectors/io_rudi_manager_write_v3.py
rudi_node_write/connectors/io_rudi_storage_write.py
rudi_node_write/connectors/rudi_node_auth.py
rudi_node_write/rudi_types/rudi_const.py
rudi_node_write/rudi_types/rudi_contact.py
rudi_node_write/rudi_types/rudi_dates.py
rudi_node_write/rudi_types/rudi_dictionary_entry.py
rudi_node_write/rudi_types/rudi_geo.py
rudi_node_write/rudi_types/rudi_licence.py
rudi_node_write/rudi_types/rudi_media.py
rudi_node_write/rudi_types/rudi_meta.py
rudi_node_write/rudi_types/rudi_meta_misc.py
rudi_node_write/rudi_types/rudi_org.py
rudi_node_write/rudi_types/serializable.py
rudi_node_write/utils/dict_utils.py
rudi_node_write/utils/err.py
rudi_node_write/utils/file_utils.py
rudi_node_write/utils/html_utils.py
rudi_node_write/utils/jwt.py
rudi_node_write/utils/list_utils.py
rudi_node_write/utils/log.py
rudi_node_write/utils/str_utils.py
rudi_node_write/utils/type_date.py
rudi_node_write/utils/typing_utils.py
rudi_node_write/utils/url_utils.py
rudi_node_write-1.3.8.dist-info/licenses/LICENCE.md
rudi_node_write-1.3.8.dist-info/METADATA
rudi_node_write-1.3.8.dist-info/WHEEL
rudi_node_write-1.3.8.dist-info/top_level.txt
rudi_node_write-1.3.8.dist-info/RECORD
